src/simple_aws_wrapper/AWS.py
src/simple_aws_wrapper/__init__.py
venv/Lib/site-packages/_black_version.py
venv/Lib/site-packages/_virtualenv.py
venv/Lib/site-packages/mypy_extensions.py
venv/Lib/site-packages/six.py
venv/Lib/site-packages/typing_extensions.py
venv/Lib/site-packages/_distutils_hack/__init__.py
venv/Lib/site-packages/_distutils_hack/override.py
venv/Lib/site-packages/aiohttp/__init__.py
venv/Lib/site-packages/aiohttp/abc.py
venv/Lib/site-packages/aiohttp/base_protocol.py
venv/Lib/site-packages/aiohttp/client.py
venv/Lib/site-packages/aiohttp/client_exceptions.py
venv/Lib/site-packages/aiohttp/client_proto.py
venv/Lib/site-packages/aiohttp/client_reqrep.py
venv/Lib/site-packages/aiohttp/client_ws.py
venv/Lib/site-packages/aiohttp/connector.py
venv/Lib/site-packages/aiohttp/cookiejar.py
venv/Lib/site-packages/aiohttp/formdata.py
venv/Lib/site-packages/aiohttp/hdrs.py
venv/Lib/site-packages/aiohttp/helpers.py
venv/Lib/site-packages/aiohttp/http.py
venv/Lib/site-packages/aiohttp/http_exceptions.py
venv/Lib/site-packages/aiohttp/http_parser.py
venv/Lib/site-packages/aiohttp/http_websocket.py
venv/Lib/site-packages/aiohttp/http_writer.py
venv/Lib/site-packages/aiohttp/locks.py
venv/Lib/site-packages/aiohttp/log.py
venv/Lib/site-packages/aiohttp/multipart.py
venv/Lib/site-packages/aiohttp/payload.py
venv/Lib/site-packages/aiohttp/payload_streamer.py
venv/Lib/site-packages/aiohttp/pytest_plugin.py
venv/Lib/site-packages/aiohttp/resolver.py
venv/Lib/site-packages/aiohttp/streams.py
venv/Lib/site-packages/aiohttp/tcp_helpers.py
venv/Lib/site-packages/aiohttp/tracing.py
venv/Lib/site-packages/aiohttp/typedefs.py
venv/Lib/site-packages/aiohttp/web.py
venv/Lib/site-packages/aiohttp/web_app.py
venv/Lib/site-packages/aiohttp/web_exceptions.py
venv/Lib/site-packages/aiohttp/web_fileresponse.py
venv/Lib/site-packages/aiohttp/web_log.py
venv/Lib/site-packages/aiohttp/web_middlewares.py
venv/Lib/site-packages/aiohttp/web_protocol.py
simple_aws_wrapper_trupyx-0.0.1.dist-info/METADATA
simple_aws_wrapper_trupyx-0.0.1.dist-info/WHEEL
simple_aws_wrapper_trupyx-0.0.1.dist-info/licenses/LICENSE
simple_aws_wrapper_trupyx-0.0.1.dist-info/RECORD
