Metadata-Version: 2.1
Name: simple_aws_wrapper_Trupyx
Version: 0.0.1
Summary: Implementazione minimale per la gestione delle risorse in cloud di AWS
Author-email: Andrea Trupia <andrea.trupia.96@gmail.com>
License-File: LICENSE
Classifier: License :: OSI Approved :: MIT License
Classifier: Operating System :: OS Independent
Classifier: Programming Language :: Python :: 3
Requires-Python: >=3.9
